pydockerize/__init__.py
pydockerize/build.py
pydockerize/config.py
pydockerize/initialize.py
pydockerize/version.py
pydockerize/default_build_files/Dockerfile
pydockerize/default_build_files/README.md
pydockerize/default_build_files/build.sh
pydockerize/default_build_files/push.sh
pydockerize/default_build_files/files/.bash_profile
pydockerize/default_build_files/files/.bashrc
pydockerize/default_build_files/files/.inputrc
pydockerize/default_build_files/files/.vimrc
pydockerize/default_project_files/service_template.sh
pydockerize/default_project_files/default/docker-compose.yml
pydockerize/default_project_files/default/environment.yml
pydockerize/tests/__init__.py
pydockerize/tests/tests.py
pydockerize-0.2.0.dist-info/LICENSE
pydockerize-0.2.0.dist-info/METADATA
pydockerize-0.2.0.dist-info/WHEEL
pydockerize-0.2.0.dist-info/entry_points.txt
pydockerize-0.2.0.dist-info/top_level.txt
pydockerize-0.2.0.dist-info/RECORD
